{
	"pages": [ //pages数组中第一项表示应用启动页，参考：https://uniapp.dcloud.io/collocation/pages
		{
			"path": "pages/index/index",
			"style": {
				"navigationBarTitleText": "发现",
				"app-plus": {
					"titleNView": false
				}
			}
		}
        ,{
            "path" : "pages/video/video",
            "style" :                                                                                    
            {
                "navigationBarTitleText": "视频",
                "enablePullDownRefresh": false
            }
            
        }
        ,{
            "path" : "pages/mine/mine",
            "style" :                                                                                    
            {
                "navigationBarTitleText": "我的",
                "enablePullDownRefresh": false
            }
            
        }
        ,{
            "path" : "pages/park/park",
            "style" :                                                                                    
            {
                "navigationBarTitleText": "云村",
                "enablePullDownRefresh": false
            }
            
        }
        ,{
            "path" : "pages/user/user",
            "style" :                                                                                    
            {
                "navigationBarTitleText": "账号",
                "enablePullDownRefresh": false
            }
            
        }
    ],
	"globalStyle": {
		"navigationBarTextStyle": "black",
		"navigationBarTitleText": "uni-app",
		"navigationBarBackgroundColor": "#F8F8F8",
		"backgroundColor": "#F8F8F8"
	},
	"uniIdRouter": {},
	"tabBar": {
		"list": [
			{
				"iconPath": "static/tabbar/home.png",
				"selectedIconPath": "static/tabbar/home_active.png",
				"pagePath": "pages/index/index",
				"text": "发现"
			},
			{
				"iconPath": "static/tabbar/video.png",
				"selectedIconPath": "static/tabbar/video_active.png",
				"pagePath": "pages/video/video",
				"text": "视频"
			},
			{
				"iconPath": "static/tabbar/mine.png",
				"selectedIconPath": "static/tabbar/mine_active.png",
				"pagePath": "pages/mine/mine",
				"text": "我的"
			},
			{
				"iconPath": "static/tabbar/park.png",
				"selectedIconPath": "static/tabbar/park_active.png",
				"pagePath": "pages/park/park",
				"text": "云村"
			},
			{
				"iconPath": "static/tabbar/user.png",
				"selectedIconPath": "static/tabbar/user_active.png",
				"pagePath": "pages/user/user",
				"text": "账号"
			}
		]
	}
}
